otio_fcpx_xml_lite_adapter/__init__.py
otio_fcpx_xml_lite_adapter/adapter.py
otio_fcpx_xml_lite_adapter/plugin_manifest.json
otio_fcpx_xml_lite_adapter/reader.py
otio_fcpx_xml_lite_adapter/utils.py
otio_fcpx_xml_lite_adapter/writer.py
otio_fcpx_xml_lite_adapter-0.2.3.dist-info/licenses/LICENSE
otio_fcpx_xml_lite_adapter-0.2.3.dist-info/METADATA
otio_fcpx_xml_lite_adapter-0.2.3.dist-info/WHEEL
otio_fcpx_xml_lite_adapter-0.2.3.dist-info/entry_points.txt
otio_fcpx_xml_lite_adapter-0.2.3.dist-info/top_level.txt
otio_fcpx_xml_lite_adapter-0.2.3.dist-info/RECORD
