Metadata-Version: 2.4
Name: otio-fcpx-xml-lite-adapter
Version: 0.2.3
Summary: OpenTimelineIO FCP X XML Lite Adapter
Author-email: Allen Day <allenday@allenday.com>
License-Expression: Apache-2.0
Project-URL: Homepage, https://github.com/allenday/otio-fcpx-xml-lite-adapter
Project-URL: Tracker, https://github.com/allenday/otio-fcpx-xml-lite-adapter/issues
Keywords: film,tv,editing,editorial,edit,non-linear,fcpx,time,otio,otio-adapter
Classifier: Development Status :: 5 - Production/Stable
Classifier: Topic :: Multimedia :: Graphics
Classifier: Topic :: Multimedia :: Video
Classifier: Topic :: Multimedia :: Video :: Display
Classifier: Topic :: Multimedia :: Video :: Non-Linear Editor
Classifier: Topic :: Software Development :: Libraries :: Python Modules
Classifier: Programming Language :: Python :: 3
Classifier: Programming Language :: Python :: 3.7
Classifier: Programming Language :: Python :: 3.8
Classifier: Programming Language :: Python :: 3.9
Classifier: Programming Language :: Python :: 3.10
Classifier: Programming Language :: Python :: 3.11
Classifier: Operating System :: OS Independent
Classifier: Natural Language :: English
Requires-Python: >=3.10
License-File: LICENSE
Requires-Dist: opentimelineio>=0.17.0
Dynamic: license-file
